musicTour/__init__.py
musicTour/musicTour.py
musicTour-1.6.0.dist-info/LICENSE.txt
musicTour-1.6.0.dist-info/METADATA
musicTour-1.6.0.dist-info/WHEEL
musicTour-1.6.0.dist-info/top_level.txt
musicTour-1.6.0.dist-info/RECORD
