Metadata-Version: 2.1
Name: musicTour
Version: 1.6.0
Summary: Get all the artists and/or all styles of the world
Author-email: Nathan Arditti <nath.arditti@yahoo.fr>
Project-URL: Homepage, https://github.com/SnowDhrop/musicTour
Classifier: Programming Language :: Python :: 3
Classifier: License :: OSI Approved :: MIT License
Classifier: Operating System :: OS Independent
Requires-Python: >=3.7
License-File: LICENSE.txt
